[
    {
        "name": "Emblem",
        "items": [
            {
                "url": "https://raw.githubusercontent.com/UnspecifiedLLC/ReleasedComponents/master/Emblem/Emblem/createemblemidentity.js",
                "version": "0.0.9",
                "display-name": "Create Emblem Identity"
            },
            {
                "url": "https://raw.githubusercontent.com/UnspecifiedLLC/ReleasedComponents/master/Emblem/Emblem/getemblemvaultsbyidentity.js",
                "version": "0.0.1",
                "display-name": "Get Emblem Vaults by Identity"
            },
            {
                "url": "https://raw.githubusercontent.com/UnspecifiedLLC/ReleasedComponents/master/Emblem/Emblem/createvault.js",
                "version": "0.0.10",
                "display-name": "Create Emblem Vault"
            },
            {
                "url": "https://raw.githubusercontent.com/UnspecifiedLLC/ReleasedComponents/master/Emblem/Emblem/getsavedemblemidentity.js",
                "version": "0.0.1",
                "display-name": "Get Saved Emblem Identity"
            },
            {
                "url": "https://raw.githubusercontent.com/UnspecifiedLLC/ReleasedComponents/master/Emblem/Emblem/getcoinbalancebyaddress.js",
                "version": "0.0.6",
                "display-name": "Get Coin Balance by Address"
            },
            {
                "url": "https://raw.githubusercontent.com/UnspecifiedLLC/ReleasedComponents/master/Emblem/Emblem/randomstring.js",
                "version": "0.0.3",
                "display-name": "Random String Generator"
            },
            {
                "url": "https://raw.githubusercontent.com/UnspecifiedLLC/ReleasedComponents/master/Emblem/Emblem/encrypt.js",
                "version": "0.0.3",
                "display-name": "Encrypt String"
            },
            {
                "url": "https://raw.githubusercontent.com/UnspecifiedLLC/ReleasedComponents/master/Emblem/Emblem/decrypt.js",
                "version": "0.0.1",
                "display-name": "Decrypt String"
            }
        ]
    },
    {
        "name": "IO",
        "items": [
            {
                "url": "https://raw.githubusercontent.com/UnspecifiedLLC/ReleasedComponents/master/Emblem/IO/csv2json.js",
                "version": "0.0.2",
                "display-name": "CSV to JSON"
            },
            {
                "url": "https://raw.githubusercontent.com/UnspecifiedLLC/ReleasedComponents/master/Emblem/IO/mergeupstream.js",
                "version": "0.0.2",
                "display-name": "Merge Upstream"
            },
            {
                "url": "https://raw.githubusercontent.com/UnspecifiedLLC/ReleasedComponents/master/Emblem/IO/transformobject.js",
                "version": "0.0.1",
                "display-name": "Transform Object"
            }
        ]
    },
    {
        "name": "Messaging",
        "items": [
            {
                "url": "https://raw.githubusercontent.com/UnspecifiedLLC/ReleasedComponents/master/Emblem/Messaging/sendsms.js",
                "version": "0.0.4",
                "display-name": "Send SMS"
            },
            {
                "url": "https://raw.githubusercontent.com/UnspecifiedLLC/ReleasedComponents/master/Emblem/Messaging/sendemail.js",
                "version": "0.0.3",
                "display-name": "Send Email"
            }
        ]
    },
    {
        "name": "CoinCap",
        "items": [
            {
                "url": "https://raw.githubusercontent.com/UnspecifiedLLC/ReleasedComponents/master/Emblem/CoinCap/assetsid.js",
                "version": "0.0.1",
                "display-name": "Get Asset Details"
            }
        ]
    },
    {
        "name": "Blockchain.com",
        "items": [
            {
                "url": "https://raw.githubusercontent.com/UnspecifiedLLC/ReleasedComponents/master/Emblem/Blockchain/bitcoinblocksws.js",
                "version": "0.0.2",
                "display-name": "Bitcoin Blocks"
            },
            {
                "url": "https://raw.githubusercontent.com/UnspecifiedLLC/ReleasedComponents/master/Emblem/Blockchain/bitcointransactionsws.js",
                "version": "0.0.2",
                "display-name": "Bitcoin Transactions"
            }
        ]
    },
    {
        "name": "Shrimpy",
        "items": [
            {
                "url": "https://raw.githubusercontent.com/UnspecifiedLLC/ReleasedComponents/master/Emblem/Shrimpy/getassetpopularity.js",
                "version": "0.0.1",
                "display-name": "Get Asset Popularity"
            },
            {
                "url": "https://raw.githubusercontent.com/UnspecifiedLLC/ReleasedComponents/master/Emblem/Shrimpy/getexchangeassets.js",
                "version": "0.0.1",
                "display-name": "Get Exchange Assets"
            },
            {
                "url": "https://raw.githubusercontent.com/UnspecifiedLLC/ReleasedComponents/master/Emblem/Shrimpy/getorderbooks.js",
                "version": "0.0.1",
                "display-name": "Get Order Books"
            }
        ]
    }
]
